sqlite_utils_sqlite_vec_sl_tmp/__init__.py
sqlite_utils_sqlite_vec_sl_tmp-0.0.2.dist-info/METADATA
sqlite_utils_sqlite_vec_sl_tmp-0.0.2.dist-info/WHEEL
sqlite_utils_sqlite_vec_sl_tmp-0.0.2.dist-info/entry_points.txt
sqlite_utils_sqlite_vec_sl_tmp-0.0.2.dist-info/top_level.txt
sqlite_utils_sqlite_vec_sl_tmp-0.0.2.dist-info/RECORD
