Metadata-Version: 2.1
Name: sqlite-utils-sqlite-vec-sl-tmp
Version: 0.0.2
Home-page: https://TODO.com
Author: TODO
License: MIT License, Apache License, Version 2.0
Requires-Dist: sqlite-utils
Requires-Dist: sqlite-vec-sl-tmp (==0.0.2)
